{
  "type":"nomad_meta_info_1_0",
  "name":"siesta_autogenerated",
  "description":"autogenerated nomad meta info for siesta parser.  The file which generates this maintained in the parser's git repository.",
  "dependencies":[{
    "relativePath":"common.nomadmetainfo.json"
  },{
    "relativePath":"public.nomadmetainfo.json"
  }],
  "metaInfos":[{
    "name":"x_siesta_input",
    "kindStr":"type_abstract_document_content",
    "description":"siesta input variables",
    "superNames":[]
  },{
    "name":"x_siesta_input_alloc_report_level",
    "description":"siesta input variable \"alloc_report_level\"",
    "superNames":["x_siesta_section_input","x_siesta_input"],
    "dtypeStr":"C"
  },{
    "name":"x_siesta_input_alloc_report_threshold",
    "description":"siesta input variable \"alloc_report_threshold\"",
    "superNames":["x_siesta_section_input","x_siesta_input"],
    "dtypeStr":"C"
  },{
    "name":"x_siesta_input_atom_debug_kb_generation",
    "description":"siesta input variable \"Atom.Debug.KB.Generation\"",
    "superNames":["x_siesta_section_input","x_siesta_input"],
    "dtypeStr":"C"
  },{
    "name":"x_siesta_input_atom_setup_only",
    "description":"siesta input variable \"Atom-Setup-Only\"",
    "superNames":["x_siesta_section_input","x_siesta_input"],
    "dtypeStr":"C"
  },{
    "name":"x_siesta_input_atomcoorformatout",
    "description":"siesta input variable \"AtomCoorFormatOut\"",
    "superNames":["x_siesta_section_input","x_siesta_input"],
    "dtypeStr":"C"
  },{
    "name":"x_siesta_input_atomiccoordinatesformat",
    "description":"siesta input variable \"AtomicCoordinatesFormat\"",
    "superNames":["x_siesta_section_input","x_siesta_input"],
    "dtypeStr":"C"
  },{
    "name":"x_siesta_input_atomleftvcte",
    "description":"siesta input variable \"AtomLeftVcte\"",
    "superNames":["x_siesta_section_input","x_siesta_input"],
    "dtypeStr":"C"
  },{
    "name":"x_siesta_input_atomrightvcte",
    "description":"siesta input variable \"AtomRightVcte\"",
    "superNames":["x_siesta_section_input","x_siesta_input"],
    "dtypeStr":"C"
  },{
    "name":"x_siesta_input_basispressure",
    "description":"siesta input variable \"BasisPressure\"",
    "superNames":["x_siesta_section_input","x_siesta_input"],
    "dtypeStr":"C"
  },{
    "name":"x_siesta_input_blocksize",
    "description":"siesta input variable \"blocksize\"",
    "superNames":["x_siesta_section_input","x_siesta_input"],
    "dtypeStr":"C"
  },{
    "name":"x_siesta_input_borncharge",
    "description":"siesta input variable \"BornCharge\"",
    "superNames":["x_siesta_section_input","x_siesta_input"],
    "dtypeStr":"C"
  },{
    "name":"x_siesta_input_buildsupercell",
    "description":"siesta input variable \"BuildSuperCell\"",
    "superNames":["x_siesta_section_input","x_siesta_input"],
    "dtypeStr":"C"
  },{
    "name":"x_siesta_input_bulklead",
    "description":"siesta input variable \"BulkLead\"",
    "superNames":["x_siesta_section_input","x_siesta_input"],
    "dtypeStr":"C"
  },{
    "name":"x_siesta_input_bulktransport",
    "description":"siesta input variable \"BulkTransport\"",
    "superNames":["x_siesta_section_input","x_siesta_input"],
    "dtypeStr":"C"
  },{
    "name":"x_siesta_input_bulktransvcellsize",
    "description":"siesta input variable \"BulkTransvCellSize\"",
    "superNames":["x_siesta_section_input","x_siesta_input"],
    "dtypeStr":"C"
  },{
    "name":"x_siesta_input_bulktransvcellsizex",
    "description":"siesta input variable \"BulkTransvCellSizeX\"",
    "superNames":["x_siesta_section_input","x_siesta_input"],
    "dtypeStr":"C"
  },{
    "name":"x_siesta_input_bulktransvcellsizey",
    "description":"siesta input variable \"BulkTransvCellSizeY\"",
    "superNames":["x_siesta_section_input","x_siesta_input"],
    "dtypeStr":"C"
  },{
    "name":"x_siesta_input_bulktransvcellsizez",
    "description":"siesta input variable \"BulkTransvCellSizeZ\"",
    "superNames":["x_siesta_section_input","x_siesta_input"],
    "dtypeStr":"C"
  },{
    "name":"x_siesta_input_calciets",
    "description":"siesta input variable \"CalcIETS\"",
    "superNames":["x_siesta_section_input","x_siesta_input"],
    "dtypeStr":"C"
  },{
    "name":"x_siesta_input_calcmpsh",
    "description":"siesta input variable \"CalcMPSH\"",
    "superNames":["x_siesta_section_input","x_siesta_input"],
    "dtypeStr":"C"
  },{
    "name":"x_siesta_input_cb_maxkappa",
    "description":"siesta input variable \"CB.MaxKappa\"",
    "superNames":["x_siesta_section_input","x_siesta_input"],
    "dtypeStr":"C"
  },{
    "name":"x_siesta_input_cb_writecomplexbands",
    "description":"siesta input variable \"CB.WriteComplexBands\"",
    "superNames":["x_siesta_section_input","x_siesta_input"],
    "dtypeStr":"C"
  },{
    "name":"x_siesta_input_cdft",
    "description":"siesta input variable \"CDFT\"",
    "superNames":["x_siesta_section_input","x_siesta_input"],
    "dtypeStr":"C"
  },{
    "name":"x_siesta_input_cdft_maxiter",
    "description":"siesta input variable \"CDFT.MaxIter\"",
    "superNames":["x_siesta_section_input","x_siesta_input"],
    "dtypeStr":"C"
  },{
    "name":"x_siesta_input_changekgridinmd",
    "description":"siesta input variable \"ChangeKgridInMD\"",
    "superNames":["x_siesta_section_input","x_siesta_input"],
    "dtypeStr":"C"
  },{
    "name":"x_siesta_input_compat_pre_v4_dm_h",
    "description":"siesta input variable \"Compat-pre-v4-DM-H\"",
    "superNames":["x_siesta_section_input","x_siesta_input"],
    "dtypeStr":"C"
  },{
    "name":"x_siesta_input_compat_pre_v4_dynamics",
    "description":"siesta input variable \"compat-pre-v4-dynamics\"",
    "superNames":["x_siesta_section_input","x_siesta_input"],
    "dtypeStr":"C"
  },{
    "name":"x_siesta_input_coop_write",
    "description":"siesta input variable \"COOP.Write\"",
    "superNames":["x_siesta_section_input","x_siesta_input"],
    "dtypeStr":"C"
  },{
    "name":"x_siesta_input_delta",
    "description":"siesta input variable \"Delta\"",
    "superNames":["x_siesta_section_input","x_siesta_input"],
    "dtypeStr":"C"
  },{
    "name":"x_siesta_input_deltaworkfunction",
    "description":"siesta input variable \"DeltaWorkfunction\"",
    "superNames":["x_siesta_section_input","x_siesta_input"],
    "dtypeStr":"C"
  },{
    "name":"x_siesta_input_diag_allinone",
    "description":"siesta input variable \"Diag.AllInOne\"",
    "superNames":["x_siesta_section_input","x_siesta_input"],
    "dtypeStr":"C"
  },{
    "name":"x_siesta_input_diag_divideandconquer",
    "description":"siesta input variable \"Diag.DivideAndConquer\"",
    "superNames":["x_siesta_section_input","x_siesta_input"],
    "dtypeStr":"C"
  },{
    "name":"x_siesta_input_diag_memory",
    "description":"siesta input variable \"Diag.Memory\"",
    "superNames":["x_siesta_section_input","x_siesta_input"],
    "dtypeStr":"C"
  },{
    "name":"x_siesta_input_diag_noexpert",
    "description":"siesta input variable \"Diag.NoExpert\"",
    "superNames":["x_siesta_section_input","x_siesta_input"],
    "dtypeStr":"C"
  },{
    "name":"x_siesta_input_diag_paralleloverk",
    "description":"siesta input variable \"Diag.ParallelOverK\"",
    "superNames":["x_siesta_section_input","x_siesta_input"],
    "dtypeStr":"C"
  },{
    "name":"x_siesta_input_diag_prerotate",
    "description":"siesta input variable \"Diag.PreRotate\"",
    "superNames":["x_siesta_section_input","x_siesta_input"],
    "dtypeStr":"C"
  },{
    "name":"x_siesta_input_diag_use2d",
    "description":"siesta input variable \"Diag.Use2D\"",
    "superNames":["x_siesta_section_input","x_siesta_input"],
    "dtypeStr":"C"
  },{
    "name":"x_siesta_input_diagmemory",
    "description":"siesta input variable \"DiagMemory\"",
    "superNames":["x_siesta_section_input","x_siesta_input"],
    "dtypeStr":"C"
  },{
    "name":"x_siesta_input_diagscale",
    "description":"siesta input variable \"DiagScale\"",
    "superNames":["x_siesta_section_input","x_siesta_input"],
    "dtypeStr":"C"
  },{
    "name":"x_siesta_input_directphi",
    "description":"siesta input variable \"DirectPhi\"",
    "superNames":["x_siesta_section_input","x_siesta_input"],
    "dtypeStr":"C"
  },{
    "name":"x_siesta_input_divideandconquer",
    "description":"siesta input variable \"DivideAndConquer\"",
    "superNames":["x_siesta_section_input","x_siesta_input"],
    "dtypeStr":"C"
  },{
    "name":"x_siesta_input_dm_allowextrapolation",
    "description":"siesta input variable \"DM.AllowExtrapolation\"",
    "superNames":["x_siesta_section_input","x_siesta_input"],
    "dtypeStr":"C"
  },{
    "name":"x_siesta_input_dm_allowreuse",
    "description":"siesta input variable \"DM.AllowReuse\"",
    "superNames":["x_siesta_section_input","x_siesta_input"],
    "dtypeStr":"C"
  },{
    "name":"x_siesta_input_dm_energytolerance",
    "description":"siesta input variable \"DM.EnergyTolerance\"",
    "superNames":["x_siesta_section_input","x_siesta_input"],
    "dtypeStr":"C"
  },{
    "name":"x_siesta_input_dm_fire_mixing",
    "description":"siesta input variable \"DM.FIRE.Mixing\"",
    "superNames":["x_siesta_section_input","x_siesta_input"],
    "dtypeStr":"C"
  },{
    "name":"x_siesta_input_dm_formattedfiles",
    "description":"siesta input variable \"DM.FormattedFiles\"",
    "superNames":["x_siesta_section_input","x_siesta_input"],
    "dtypeStr":"C"
  },{
    "name":"x_siesta_input_dm_formattedinput",
    "description":"siesta input variable \"DM.FormattedInput\"",
    "superNames":["x_siesta_section_input","x_siesta_input"],
    "dtypeStr":"C"
  },{
    "name":"x_siesta_input_dm_formattedoutput",
    "description":"siesta input variable \"DM.FormattedOutput\"",
    "superNames":["x_siesta_section_input","x_siesta_input"],
    "dtypeStr":"C"
  },{
    "name":"x_siesta_input_dm_harristolerance",
    "description":"siesta input variable \"DM.HarrisTolerance\"",
    "superNames":["x_siesta_section_input","x_siesta_input"],
    "dtypeStr":"C"
  },{
    "name":"x_siesta_input_dm_kickmixingweight",
    "description":"siesta input variable \"DM.KickMixingWeight\"",
    "superNames":["x_siesta_section_input","x_siesta_input"],
    "dtypeStr":"C"
  },{
    "name":"x_siesta_input_dm_mixingweight",
    "description":"siesta input variable \"DM.MixingWeight\"",
    "superNames":["x_siesta_section_input","x_siesta_input"],
    "dtypeStr":"C"
  },{
    "name":"x_siesta_input_dm_mixscf1",
    "description":"siesta input variable \"DM.MixSCF1\"",
    "superNames":["x_siesta_section_input","x_siesta_input"],
    "dtypeStr":"C"
  },{
    "name":"x_siesta_input_dm_normalizationtolerance",
    "description":"siesta input variable \"DM.NormalizationTolerance\"",
    "superNames":["x_siesta_section_input","x_siesta_input"],
    "dtypeStr":"C"
  },{
    "name":"x_siesta_input_dm_normalizeduringscf",
    "description":"siesta input variable \"DM.NormalizeDuringSCF\"",
    "superNames":["x_siesta_section_input","x_siesta_input"],
    "dtypeStr":"C"
  },{
    "name":"x_siesta_input_dm_numberbroyden",
    "description":"siesta input variable \"DM.NumberBroyden\"",
    "superNames":["x_siesta_section_input","x_siesta_input"],
    "dtypeStr":"C"
  },{
    "name":"x_siesta_input_dm_numberkick",
    "description":"siesta input variable \"DM.NumberKick\"",
    "superNames":["x_siesta_section_input","x_siesta_input"],
    "dtypeStr":"C"
  },{
    "name":"x_siesta_input_dm_numberpulay",
    "description":"siesta input variable \"DM.NumberPulay\"",
    "superNames":["x_siesta_section_input","x_siesta_input"],
    "dtypeStr":"C"
  },{
    "name":"x_siesta_input_dm_occupancytolerance",
    "description":"siesta input variable \"DM.OccupancyTolerance\"",
    "superNames":["x_siesta_section_input","x_siesta_input"],
    "dtypeStr":"C"
  },{
    "name":"x_siesta_input_dm_pulay_avoid_first_after_kick",
    "description":"siesta input variable \"DM.Pulay.Avoid.First.After.Kick\"",
    "superNames":["x_siesta_section_input","x_siesta_input"],
    "dtypeStr":"C"
  },{
    "name":"x_siesta_input_dm_pulayonfile",
    "description":"siesta input variable \"DM.PulayOnFile\"",
    "superNames":["x_siesta_section_input","x_siesta_input"],
    "dtypeStr":"C"
  },{
    "name":"x_siesta_input_dm_requireenergyconvergence",
    "description":"siesta input variable \"DM.RequireEnergyConvergence\"",
    "superNames":["x_siesta_section_input","x_siesta_input"],
    "dtypeStr":"C"
  },{
    "name":"x_siesta_input_dm_requireharrisconvergence",
    "description":"siesta input variable \"DM.RequireHarrisConvergence\"",
    "superNames":["x_siesta_section_input","x_siesta_input"],
    "dtypeStr":"C"
  },{
    "name":"x_siesta_input_dm_tolerance",
    "description":"siesta input variable \"DM.Tolerance\"",
    "superNames":["x_siesta_section_input","x_siesta_input"],
    "dtypeStr":"C"
  },{
    "name":"x_siesta_input_dm_usesavedm",
    "description":"siesta input variable \"DM.UseSaveDM\"",
    "superNames":["x_siesta_section_input","x_siesta_input"],
    "dtypeStr":"C"
  },{
    "name":"x_siesta_input_electronictemperature",
    "description":"siesta input variable \"ElectronicTemperature\"",
    "superNames":["x_siesta_section_input","x_siesta_input"],
    "dtypeStr":"C"
  },{
    "name":"x_siesta_input_em_addrhogate",
    "description":"siesta input variable \"EM.AddRhoGate\"",
    "superNames":["x_siesta_section_input","x_siesta_input"],
    "dtypeStr":"C"
  },{
    "name":"x_siesta_input_em_addv",
    "description":"siesta input variable \"EM.addV\"",
    "superNames":["x_siesta_section_input","x_siesta_input"],
    "dtypeStr":"C"
  },{
    "name":"x_siesta_input_em_addvgisolatedlocalcharges",
    "description":"siesta input variable \"EM.AddVgIsolatedLocalCharges\"",
    "superNames":["x_siesta_section_input","x_siesta_input"],
    "dtypeStr":"C"
  },{
    "name":"x_siesta_input_em_coopcalculate",
    "description":"siesta input variable \"EM.COOPCalculate\"",
    "superNames":["x_siesta_section_input","x_siesta_input"],
    "dtypeStr":"C"
  },{
    "name":"x_siesta_input_em_coopnumberofbonds",
    "description":"siesta input variable \"EM.COOPNumberOfBonds\"",
    "superNames":["x_siesta_section_input","x_siesta_input"],
    "dtypeStr":"C"
  },{
    "name":"x_siesta_input_em_debugrhogate",
    "description":"siesta input variable \"EM.DebugRhoGate\"",
    "superNames":["x_siesta_section_input","x_siesta_input"],
    "dtypeStr":"C"
  },{
    "name":"x_siesta_input_em_netrhogatecharge",
    "description":"siesta input variable \"EM.NetRhoGateCharge\"",
    "superNames":["x_siesta_section_input","x_siesta_input"],
    "dtypeStr":"C"
  },{
    "name":"x_siesta_input_em_printlimits",
    "description":"siesta input variable \"EM.PrintLimits\"",
    "superNames":["x_siesta_section_input","x_siesta_input"],
    "dtypeStr":"C"
  },{
    "name":"x_siesta_input_em_rhogatelxmax",
    "description":"siesta input variable \"EM.RhoGateLxMax\"",
    "superNames":["x_siesta_section_input","x_siesta_input"],
    "dtypeStr":"C"
  },{
    "name":"x_siesta_input_em_rhogatelxmin",
    "description":"siesta input variable \"EM.RhoGateLxMin\"",
    "superNames":["x_siesta_section_input","x_siesta_input"],
    "dtypeStr":"C"
  },{
    "name":"x_siesta_input_em_rhogatelymax",
    "description":"siesta input variable \"EM.RhoGateLyMax\"",
    "superNames":["x_siesta_section_input","x_siesta_input"],
    "dtypeStr":"C"
  },{
    "name":"x_siesta_input_em_rhogatelymin",
    "description":"siesta input variable \"EM.RhoGateLyMin\"",
    "superNames":["x_siesta_section_input","x_siesta_input"],
    "dtypeStr":"C"
  },{
    "name":"x_siesta_input_em_rhogatelzmax",
    "description":"siesta input variable \"EM.RhoGateLzMax\"",
    "superNames":["x_siesta_section_input","x_siesta_input"],
    "dtypeStr":"C"
  },{
    "name":"x_siesta_input_em_rhogatelzmin",
    "description":"siesta input variable \"EM.RhoGateLzMin\"",
    "superNames":["x_siesta_section_input","x_siesta_input"],
    "dtypeStr":"C"
  },{
    "name":"x_siesta_input_em_timereversal",
    "description":"siesta input variable \"EM.TimeReversal\"",
    "superNames":["x_siesta_section_input","x_siesta_input"],
    "dtypeStr":"C"
  },{
    "name":"x_siesta_input_em_timings",
    "description":"siesta input variable \"EM.Timings\"",
    "superNames":["x_siesta_section_input","x_siesta_input"],
    "dtypeStr":"C"
  },{
    "name":"x_siesta_input_em_trcaddvcdft",
    "description":"siesta input variable \"EM.TRCAddVCDFT\"",
    "superNames":["x_siesta_section_input","x_siesta_input"],
    "dtypeStr":"C"
  },{
    "name":"x_siesta_input_empdoskso",
    "description":"siesta input variable \"EMPDOSKSO\"",
    "superNames":["x_siesta_section_input","x_siesta_input"],
    "dtypeStr":"C"
  },{
    "name":"x_siesta_input_emtransport",
    "description":"siesta input variable \"EMTransport\"",
    "superNames":["x_siesta_section_input","x_siesta_input"],
    "dtypeStr":"C"
  },{
    "name":"x_siesta_input_endblock",
    "description":"siesta input variable \"%endblock\"",
    "superNames":["x_siesta_section_input","x_siesta_input"],
    "dtypeStr":"C"
  },{
    "name":"x_siesta_input_energlowestbound",
    "description":"siesta input variable \"EnergLowestBound\"",
    "superNames":["x_siesta_section_input","x_siesta_input"],
    "dtypeStr":"C"
  },{
    "name":"x_siesta_input_fdf_debug",
    "description":"siesta input variable \"fdf-debug\"",
    "superNames":["x_siesta_section_input","x_siesta_input"],
    "dtypeStr":"C"
  },{
    "name":"x_siesta_input_filtercutoff",
    "description":"siesta input variable \"FilterCutoff\"",
    "superNames":["x_siesta_section_input","x_siesta_input"],
    "dtypeStr":"C"
  },{
    "name":"x_siesta_input_filtertol",
    "description":"siesta input variable \"FilterTol\"",
    "superNames":["x_siesta_section_input","x_siesta_input"],
    "dtypeStr":"C"
  },{
    "name":"x_siesta_input_finaltransmrange",
    "description":"siesta input variable \"FinalTransmRange\"",
    "superNames":["x_siesta_section_input","x_siesta_input"],
    "dtypeStr":"C"
  },{
    "name":"x_siesta_input_fixauxiliarycell",
    "description":"siesta input variable \"FixAuxiliaryCell\"",
    "superNames":["x_siesta_section_input","x_siesta_input"],
    "dtypeStr":"C"
  },{
    "name":"x_siesta_input_fixauxillarycell",
    "description":"siesta input variable \"FixAuxillaryCell\"",
    "superNames":["x_siesta_section_input","x_siesta_input"],
    "dtypeStr":"C"
  },{
    "name":"x_siesta_input_fixspin",
    "description":"siesta input variable \"FixSpin\"",
    "superNames":["x_siesta_section_input","x_siesta_input"],
    "dtypeStr":"C"
  },{
    "name":"x_siesta_input_forceauxcell",
    "description":"siesta input variable \"ForceAuxCell\"",
    "superNames":["x_siesta_section_input","x_siesta_input"],
    "dtypeStr":"C"
  },{
    "name":"x_siesta_input_fullramp",
    "description":"siesta input variable \"FullRamp\"",
    "superNames":["x_siesta_section_input","x_siesta_input"],
    "dtypeStr":"C"
  },{
    "name":"x_siesta_input_harris_functional",
    "description":"siesta input variable \"Harris_functional\"",
    "superNames":["x_siesta_section_input","x_siesta_input"],
    "dtypeStr":"C"
  },{
    "name":"x_siesta_input_hartreeleadsbottom",
    "description":"siesta input variable \"HartreeLeadsBottom\"",
    "superNames":["x_siesta_section_input","x_siesta_input"],
    "dtypeStr":"C"
  },{
    "name":"x_siesta_input_hartreeleadsleft",
    "description":"siesta input variable \"HartreeLeadsLeft\"",
    "superNames":["x_siesta_section_input","x_siesta_input"],
    "dtypeStr":"C"
  },{
    "name":"x_siesta_input_hartreeleadsright",
    "description":"siesta input variable \"HartreeLeadsRight\"",
    "superNames":["x_siesta_section_input","x_siesta_input"],
    "dtypeStr":"C"
  },{
    "name":"x_siesta_input_hsetuponly",
    "description":"siesta input variable \"HSetupOnly\"",
    "superNames":["x_siesta_section_input","x_siesta_input"],
    "dtypeStr":"C"
  },{
    "name":"x_siesta_input_ik_select",
    "description":"siesta input variable \"Ik_Select\"",
    "superNames":["x_siesta_section_input","x_siesta_input"],
    "dtypeStr":"C"
  },{
    "name":"x_siesta_input_inittransmrange",
    "description":"siesta input variable \"InitTransmRange\"",
    "superNames":["x_siesta_section_input","x_siesta_input"],
    "dtypeStr":"C"
  },{
    "name":"x_siesta_input_inittransport",
    "description":"siesta input variable \"InitTransport\"",
    "superNames":["x_siesta_section_input","x_siesta_input"],
    "dtypeStr":"C"
  },{
    "name":"x_siesta_input_kb_new_reference_orbitals",
    "description":"siesta input variable \"KB.New.Reference.Orbitals\"",
    "superNames":["x_siesta_section_input","x_siesta_input"],
    "dtypeStr":"C"
  },{
    "name":"x_siesta_input_kb_rmax",
    "description":"siesta input variable \"KB.Rmax\"",
    "superNames":["x_siesta_section_input","x_siesta_input"],
    "dtypeStr":"C"
  },{
    "name":"x_siesta_input_kgrid_cutoff",
    "description":"siesta input variable \"kgrid_cutoff\"",
    "superNames":["x_siesta_section_input","x_siesta_input"],
    "dtypeStr":"C"
  },{
    "name":"x_siesta_input_latticeconstant",
    "description":"siesta input variable \"LatticeConstant\"",
    "superNames":["x_siesta_section_input","x_siesta_input"],
    "dtypeStr":"C"
  },{
    "name":"x_siesta_input_ldau_method",
    "description":"siesta input variable \"LDAU_METHOD\"",
    "superNames":["x_siesta_section_input","x_siesta_input"],
    "dtypeStr":"C"
  },{
    "name":"x_siesta_input_ldau_units",
    "description":"siesta input variable \"LDAU.units\"",
    "superNames":["x_siesta_section_input","x_siesta_input"],
    "dtypeStr":"C"
  },{
    "name":"x_siesta_input_ldauforces",
    "description":"siesta input variable \"LDAUForces\"",
    "superNames":["x_siesta_section_input","x_siesta_input"],
    "dtypeStr":"C"
  },{
    "name":"x_siesta_input_longoutput",
    "description":"siesta input variable \"LongOutput\"",
    "superNames":["x_siesta_section_input","x_siesta_input"],
    "dtypeStr":"C"
  },{
    "name":"x_siesta_input_maxbonddistance",
    "description":"siesta input variable \"MaxBondDistance\"",
    "superNames":["x_siesta_section_input","x_siesta_input"],
    "dtypeStr":"C"
  },{
    "name":"x_siesta_input_maxscfiterations",
    "description":"siesta input variable \"MaxSCFIterations\"",
    "superNames":["x_siesta_section_input","x_siesta_input"],
    "dtypeStr":"C"
  },{
    "name":"x_siesta_input_md_annealoption",
    "description":"siesta input variable \"MD.AnnealOption\"",
    "superNames":["x_siesta_section_input","x_siesta_input"],
    "dtypeStr":"C"
  },{
    "name":"x_siesta_input_md_bulkmodulus",
    "description":"siesta input variable \"MD.BulkModulus\"",
    "superNames":["x_siesta_section_input","x_siesta_input"],
    "dtypeStr":"C"
  },{
    "name":"x_siesta_input_md_fcacousticsumrule",
    "description":"siesta input variable \"MD.FCAcousticSumRule\"",
    "superNames":["x_siesta_section_input","x_siesta_input"],
    "dtypeStr":"C"
  },{
    "name":"x_siesta_input_md_fcatomrestart",
    "description":"siesta input variable \"MD.FCAtomRestart\"",
    "superNames":["x_siesta_section_input","x_siesta_input"],
    "dtypeStr":"C"
  },{
    "name":"x_siesta_input_md_fcaxisrestart",
    "description":"siesta input variable \"MD.FCAxisRestart\"",
    "superNames":["x_siesta_section_input","x_siesta_input"],
    "dtypeStr":"C"
  },{
    "name":"x_siesta_input_md_fcdispl",
    "description":"siesta input variable \"MD.FCDispl\"",
    "superNames":["x_siesta_section_input","x_siesta_input"],
    "dtypeStr":"C"
  },{
    "name":"x_siesta_input_md_fceigenvectors",
    "description":"siesta input variable \"MD.FCEigenVectors\"",
    "superNames":["x_siesta_section_input","x_siesta_input"],
    "dtypeStr":"C"
  },{
    "name":"x_siesta_input_md_fcfirst",
    "description":"siesta input variable \"MD.FCfirst\"",
    "superNames":["x_siesta_section_input","x_siesta_input"],
    "dtypeStr":"C"
  },{
    "name":"x_siesta_input_md_fcir",
    "description":"siesta input variable \"MD.FCIR\"",
    "superNames":["x_siesta_section_input","x_siesta_input"],
    "dtypeStr":"C"
  },{
    "name":"x_siesta_input_md_fclast",
    "description":"siesta input variable \"MD.FClast\"",
    "superNames":["x_siesta_section_input","x_siesta_input"],
    "dtypeStr":"C"
  },{
    "name":"x_siesta_input_md_fcread",
    "description":"siesta input variable \"MD.FCRead\"",
    "superNames":["x_siesta_section_input","x_siesta_input"],
    "dtypeStr":"C"
  },{
    "name":"x_siesta_input_md_finaltimestep",
    "description":"siesta input variable \"MD.FinalTimeStep\"",
    "superNames":["x_siesta_section_input","x_siesta_input"],
    "dtypeStr":"C"
  },{
    "name":"x_siesta_input_md_firequench",
    "description":"siesta input variable \"MD.FireQuench\"",
    "superNames":["x_siesta_section_input","x_siesta_input"],
    "dtypeStr":"C"
  },{
    "name":"x_siesta_input_md_initialtemperature",
    "description":"siesta input variable \"MD.InitialTemperature\"",
    "superNames":["x_siesta_section_input","x_siesta_input"],
    "dtypeStr":"C"
  },{
    "name":"x_siesta_input_md_initialtimestep",
    "description":"siesta input variable \"MD.InitialTimeStep\"",
    "superNames":["x_siesta_section_input","x_siesta_input"],
    "dtypeStr":"C"
  },{
    "name":"x_siesta_input_md_lengthtimestep",
    "description":"siesta input variable \"MD.LengthTimeStep\"",
    "superNames":["x_siesta_section_input","x_siesta_input"],
    "dtypeStr":"C"
  },{
    "name":"x_siesta_input_md_maxcgdispl",
    "description":"siesta input variable \"MD.MaxCGDispl\"",
    "superNames":["x_siesta_section_input","x_siesta_input"],
    "dtypeStr":"C"
  },{
    "name":"x_siesta_input_md_maxforcetol",
    "description":"siesta input variable \"MD.MaxForceTol\"",
    "superNames":["x_siesta_section_input","x_siesta_input"],
    "dtypeStr":"C"
  },{
    "name":"x_siesta_input_md_maxstresstol",
    "description":"siesta input variable \"MD.MaxStressTol\"",
    "superNames":["x_siesta_section_input","x_siesta_input"],
    "dtypeStr":"C"
  },{
    "name":"x_siesta_input_md_nosemass",
    "description":"siesta input variable \"MD.NoseMass\"",
    "superNames":["x_siesta_section_input","x_siesta_input"],
    "dtypeStr":"C"
  },{
    "name":"x_siesta_input_md_numcgsteps",
    "description":"siesta input variable \"MD.NumCGsteps\"",
    "superNames":["x_siesta_section_input","x_siesta_input"],
    "dtypeStr":"C"
  },{
    "name":"x_siesta_input_md_numnebsteps",
    "description":"siesta input variable \"MD.NumNEBsteps\"",
    "superNames":["x_siesta_section_input","x_siesta_input"],
    "dtypeStr":"C"
  },{
    "name":"x_siesta_input_md_parrinellorahmanmass",
    "description":"siesta input variable \"MD.ParrinelloRahmanMass\"",
    "superNames":["x_siesta_section_input","x_siesta_input"],
    "dtypeStr":"C"
  },{
    "name":"x_siesta_input_md_quench",
    "description":"siesta input variable \"MD.Quench\"",
    "superNames":["x_siesta_section_input","x_siesta_input"],
    "dtypeStr":"C"
  },{
    "name":"x_siesta_input_md_relaxcellonly",
    "description":"siesta input variable \"MD.RelaxCellOnly\"",
    "superNames":["x_siesta_section_input","x_siesta_input"],
    "dtypeStr":"C"
  },{
    "name":"x_siesta_input_md_removeintramolecularpressure",
    "description":"siesta input variable \"MD.RemoveIntraMolecularPressure\"",
    "superNames":["x_siesta_section_input","x_siesta_input"],
    "dtypeStr":"C"
  },{
    "name":"x_siesta_input_md_targetpressure",
    "description":"siesta input variable \"MD.TargetPressure\"",
    "superNames":["x_siesta_section_input","x_siesta_input"],
    "dtypeStr":"C"
  },{
    "name":"x_siesta_input_md_targettemperature",
    "description":"siesta input variable \"MD.TargetTemperature\"",
    "superNames":["x_siesta_section_input","x_siesta_input"],
    "dtypeStr":"C"
  },{
    "name":"x_siesta_input_md_taurelax",
    "description":"siesta input variable \"MD.TauRelax\"",
    "superNames":["x_siesta_section_input","x_siesta_input"],
    "dtypeStr":"C"
  },{
    "name":"x_siesta_input_md_timing",
    "description":"siesta input variable \"MD.Timing\"",
    "superNames":["x_siesta_section_input","x_siesta_input"],
    "dtypeStr":"C"
  },{
    "name":"x_siesta_input_md_trcsampling",
    "description":"siesta input variable \"MD.TRCSampling\"",
    "superNames":["x_siesta_section_input","x_siesta_input"],
    "dtypeStr":"C"
  },{
    "name":"x_siesta_input_md_trcskip",
    "description":"siesta input variable \"MD.TRCSkip\"",
    "superNames":["x_siesta_section_input","x_siesta_input"],
    "dtypeStr":"C"
  },{
    "name":"x_siesta_input_md_typeofrun",
    "description":"siesta input variable \"MD.TypeOfRun\"",
    "superNames":["x_siesta_section_input","x_siesta_input"],
    "dtypeStr":"C"
  },{
    "name":"x_siesta_input_md_usesavecg",
    "description":"siesta input variable \"MD.UseSaveCG\"",
    "superNames":["x_siesta_section_input","x_siesta_input"],
    "dtypeStr":"C"
  },{
    "name":"x_siesta_input_md_usesaveneb",
    "description":"siesta input variable \"MD.UseSaveNEB\"",
    "superNames":["x_siesta_section_input","x_siesta_input"],
    "dtypeStr":"C"
  },{
    "name":"x_siesta_input_md_usesavexv",
    "description":"siesta input variable \"MD.UseSaveXV\"",
    "superNames":["x_siesta_section_input","x_siesta_input"],
    "dtypeStr":"C"
  },{
    "name":"x_siesta_input_md_usesavezm",
    "description":"siesta input variable \"MD.UseSaveZM\"",
    "superNames":["x_siesta_section_input","x_siesta_input"],
    "dtypeStr":"C"
  },{
    "name":"x_siesta_input_md_usestructfile",
    "description":"siesta input variable \"MD.UseStructFile\"",
    "superNames":["x_siesta_section_input","x_siesta_input"],
    "dtypeStr":"C"
  },{
    "name":"x_siesta_input_md_variablecell",
    "description":"siesta input variable \"MD.VariableCell\"",
    "superNames":["x_siesta_section_input","x_siesta_input"],
    "dtypeStr":"C"
  },{
    "name":"x_siesta_input_meshcutoff",
    "description":"siesta input variable \"MeshCutoff\"",
    "superNames":["x_siesta_section_input","x_siesta_input"],
    "dtypeStr":"C"
  },{
    "name":"x_siesta_input_meshsubdivisions",
    "description":"siesta input variable \"MeshSubDivisions\"",
    "superNames":["x_siesta_section_input","x_siesta_input"],
    "dtypeStr":"C"
  },{
    "name":"x_siesta_input_minscfiterations",
    "description":"siesta input variable \"MinSCFIterations\"",
    "superNames":["x_siesta_section_input","x_siesta_input"],
    "dtypeStr":"C"
  },{
    "name":"x_siesta_input_mixcharge",
    "description":"siesta input variable \"MixCharge\"",
    "superNames":["x_siesta_section_input","x_siesta_input"],
    "dtypeStr":"C"
  },{
    "name":"x_siesta_input_mixedparallel",
    "description":"siesta input variable \"MixedParallel\"",
    "superNames":["x_siesta_section_input","x_siesta_input"],
    "dtypeStr":"C"
  },{
    "name":"x_siesta_input_mixhamiltonian",
    "description":"siesta input variable \"MixHamiltonian\"",
    "superNames":["x_siesta_section_input","x_siesta_input"],
    "dtypeStr":"C"
  },{
    "name":"x_siesta_input_mm_cutoff",
    "description":"siesta input variable \"MM.Cutoff\"",
    "superNames":["x_siesta_section_input","x_siesta_input"],
    "dtypeStr":"C"
  },{
    "name":"x_siesta_input_mm_unitsdistance",
    "description":"siesta input variable \"MM.UnitsDistance\"",
    "superNames":["x_siesta_section_input","x_siesta_input"],
    "dtypeStr":"C"
  },{
    "name":"x_siesta_input_mm_unitsenergy",
    "description":"siesta input variable \"MM.UnitsEnergy\"",
    "superNames":["x_siesta_section_input","x_siesta_input"],
    "dtypeStr":"C"
  },{
    "name":"x_siesta_input_monitorforcesinscf",
    "description":"siesta input variable \"MonitorForcesInSCF\"",
    "superNames":["x_siesta_section_input","x_siesta_input"],
    "dtypeStr":"C"
  },{
    "name":"x_siesta_input_mpshatomfirst",
    "description":"siesta input variable \"MPSHAtomFirst\"",
    "superNames":["x_siesta_section_input","x_siesta_input"],
    "dtypeStr":"C"
  },{
    "name":"x_siesta_input_mpshatomlast",
    "description":"siesta input variable \"MPSHAtomLast\"",
    "superNames":["x_siesta_section_input","x_siesta_input"],
    "dtypeStr":"C"
  },{
    "name":"x_siesta_input_mpshorbfirst",
    "description":"siesta input variable \"MPSHOrbFirst\"",
    "superNames":["x_siesta_section_input","x_siesta_input"],
    "dtypeStr":"C"
  },{
    "name":"x_siesta_input_mpshorblast",
    "description":"siesta input variable \"MPSHOrbLast\"",
    "superNames":["x_siesta_section_input","x_siesta_input"],
    "dtypeStr":"C"
  },{
    "name":"x_siesta_input_mullikeninscf",
    "description":"siesta input variable \"MullikenInSCF\"",
    "superNames":["x_siesta_section_input","x_siesta_input"],
    "dtypeStr":"C"
  },{
    "name":"x_siesta_input_naiveauxiliarycell",
    "description":"siesta input variable \"NaiveAuxiliaryCell\"",
    "superNames":["x_siesta_section_input","x_siesta_input"],
    "dtypeStr":"C"
  },{
    "name":"x_siesta_input_nc_orbitalrotationend",
    "description":"siesta input variable \"NC.OrbitalRotationEnd\"",
    "superNames":["x_siesta_section_input","x_siesta_input"],
    "dtypeStr":"C"
  },{
    "name":"x_siesta_input_nc_orbitalrotationstart",
    "description":"siesta input variable \"NC.OrbitalRotationStart\"",
    "superNames":["x_siesta_section_input","x_siesta_input"],
    "dtypeStr":"C"
  },{
    "name":"x_siesta_input_neb_skipedge",
    "description":"siesta input variable \"NEB.SkipEdge\"",
    "superNames":["x_siesta_section_input","x_siesta_input"],
    "dtypeStr":"C"
  },{
    "name":"x_siesta_input_neglnonoverlapint",
    "description":"siesta input variable \"NeglNonOverlapInt\"",
    "superNames":["x_siesta_section_input","x_siesta_input"],
    "dtypeStr":"C"
  },{
    "name":"x_siesta_input_nenergimcircle",
    "description":"siesta input variable \"NenergImCircle\"",
    "superNames":["x_siesta_section_input","x_siesta_input"],
    "dtypeStr":"C"
  },{
    "name":"x_siesta_input_nenergimline",
    "description":"siesta input variable \"NenergImLine\"",
    "superNames":["x_siesta_section_input","x_siesta_input"],
    "dtypeStr":"C"
  },{
    "name":"x_siesta_input_nenergreal",
    "description":"siesta input variable \"NEnergReal\"",
    "superNames":["x_siesta_section_input","x_siesta_input"],
    "dtypeStr":"C"
  },{
    "name":"x_siesta_input_netcharge",
    "description":"siesta input variable \"NetCharge\"",
    "superNames":["x_siesta_section_input","x_siesta_input"],
    "dtypeStr":"C"
  },{
    "name":"x_siesta_input_nivpoints",
    "description":"siesta input variable \"NIVPoints\"",
    "superNames":["x_siesta_section_input","x_siesta_input"],
    "dtypeStr":"C"
  },{
    "name":"x_siesta_input_noncollinearspin",
    "description":"siesta input variable \"NonCollinearSpin\"",
    "superNames":["x_siesta_section_input","x_siesta_input"],
    "dtypeStr":"C"
  },{
    "name":"x_siesta_input_npoles",
    "description":"siesta input variable \"NPoles\"",
    "superNames":["x_siesta_section_input","x_siesta_input"],
    "dtypeStr":"C"
  },{
    "name":"x_siesta_input_nslices",
    "description":"siesta input variable \"NSlices\"",
    "superNames":["x_siesta_section_input","x_siesta_input"],
    "dtypeStr":"C"
  },{
    "name":"x_siesta_input_ntransmpoints",
    "description":"siesta input variable \"NTransmPoints\"",
    "superNames":["x_siesta_section_input","x_siesta_input"],
    "dtypeStr":"C"
  },{
    "name":"x_siesta_input_number_of_species",
    "description":"siesta input variable \"Number_of_species\"",
    "superNames":["x_siesta_section_input","x_siesta_input"],
    "dtypeStr":"C"
  },{
    "name":"x_siesta_input_numberlinearmix",
    "description":"siesta input variable \"NumberLinearMix\"",
    "superNames":["x_siesta_section_input","x_siesta_input"],
    "dtypeStr":"C"
  },{
    "name":"x_siesta_input_numberofatoms",
    "description":"siesta input variable \"NumberOfAtoms\"",
    "superNames":["x_siesta_section_input","x_siesta_input"],
    "dtypeStr":"C"
  },{
    "name":"x_siesta_input_numberofeigenstates",
    "description":"siesta input variable \"NumberOfEigenStates\"",
    "superNames":["x_siesta_section_input","x_siesta_input"],
    "dtypeStr":"C"
  },{
    "name":"x_siesta_input_numberofspecies",
    "description":"siesta input variable \"NumberOfSpecies\"",
    "superNames":["x_siesta_section_input","x_siesta_input"],
    "dtypeStr":"C"
  },{
    "name":"x_siesta_input_numskipwritedm",
    "description":"siesta input variable \"NumSkipWriteDM\"",
    "superNames":["x_siesta_section_input","x_siesta_input"],
    "dtypeStr":"C"
  },{
    "name":"x_siesta_input_occupationfunction",
    "description":"siesta input variable \"OccupationFunction\"",
    "superNames":["x_siesta_section_input","x_siesta_input"],
    "dtypeStr":"C"
  },{
    "name":"x_siesta_input_on_chemicalpotential",
    "description":"siesta input variable \"ON.ChemicalPotential\"",
    "superNames":["x_siesta_section_input","x_siesta_input"],
    "dtypeStr":"C"
  },{
    "name":"x_siesta_input_on_chemicalpotentialorder",
    "description":"siesta input variable \"ON.ChemicalPotentialOrder\"",
    "superNames":["x_siesta_section_input","x_siesta_input"],
    "dtypeStr":"C"
  },{
    "name":"x_siesta_input_on_chemicalpotentialrc",
    "description":"siesta input variable \"ON.ChemicalPotentialRc\"",
    "superNames":["x_siesta_section_input","x_siesta_input"],
    "dtypeStr":"C"
  },{
    "name":"x_siesta_input_on_chemicalpotentialtemperature",
    "description":"siesta input variable \"ON.ChemicalPotentialTemperature\"",
    "superNames":["x_siesta_section_input","x_siesta_input"],
    "dtypeStr":"C"
  },{
    "name":"x_siesta_input_on_chemicalpotentialuse",
    "description":"siesta input variable \"ON.ChemicalPotentialUse\"",
    "superNames":["x_siesta_section_input","x_siesta_input"],
    "dtypeStr":"C"
  },{
    "name":"x_siesta_input_on_eta",
    "description":"siesta input variable \"ON.eta\"",
    "superNames":["x_siesta_section_input","x_siesta_input"],
    "dtypeStr":"C"
  },{
    "name":"x_siesta_input_on_eta_alpha",
    "description":"siesta input variable \"ON.eta_alpha\"",
    "superNames":["x_siesta_section_input","x_siesta_input"],
    "dtypeStr":"C"
  },{
    "name":"x_siesta_input_on_eta_beta",
    "description":"siesta input variable \"ON.eta_beta\"",
    "superNames":["x_siesta_section_input","x_siesta_input"],
    "dtypeStr":"C"
  },{
    "name":"x_siesta_input_on_etol",
    "description":"siesta input variable \"ON.etol\"",
    "superNames":["x_siesta_section_input","x_siesta_input"],
    "dtypeStr":"C"
  },{
    "name":"x_siesta_input_on_functional",
    "description":"siesta input variable \"ON.functional\"",
    "superNames":["x_siesta_section_input","x_siesta_input"],
    "dtypeStr":"C"
  },{
    "name":"x_siesta_input_on_maxnumiter",
    "description":"siesta input variable \"ON.MaxNumIter\"",
    "superNames":["x_siesta_section_input","x_siesta_input"],
    "dtypeStr":"C"
  },{
    "name":"x_siesta_input_on_rclwf",
    "description":"siesta input variable \"On.RcLWF\"",
    "superNames":["x_siesta_section_input","x_siesta_input"],
    "dtypeStr":"C"
  },{
    "name":"x_siesta_input_on_usesavelwf",
    "description":"siesta input variable \"ON.UseSaveLWF\"",
    "superNames":["x_siesta_section_input","x_siesta_input"],
    "dtypeStr":"C"
  },{
    "name":"x_siesta_input_opticalcalculation",
    "description":"siesta input variable \"OpticalCalculation\"",
    "superNames":["x_siesta_section_input","x_siesta_input"],
    "dtypeStr":"C"
  },{
    "name":"x_siesta_input_optim_broyden",
    "description":"siesta input variable \"Optim.Broyden\"",
    "superNames":["x_siesta_section_input","x_siesta_input"],
    "dtypeStr":"C"
  },{
    "name":"x_siesta_input_output_structure_only",
    "description":"siesta input variable \"Output-Structure-Only\"",
    "superNames":["x_siesta_section_input","x_siesta_input"],
    "dtypeStr":"C"
  },{
    "name":"x_siesta_input_pao_basissize",
    "description":"siesta input variable \"PAO.BasisSize\"",
    "superNames":["x_siesta_section_input","x_siesta_input"],
    "dtypeStr":"C"
  },{
    "name":"x_siesta_input_pao_basistype",
    "description":"siesta input variable \"PAO.BasisType\"",
    "superNames":["x_siesta_section_input","x_siesta_input"],
    "dtypeStr":"C"
  },{
    "name":"x_siesta_input_pao_energyshift",
    "description":"siesta input variable \"PAO.EnergyShift\"",
    "superNames":["x_siesta_section_input","x_siesta_input"],
    "dtypeStr":"C"
  },{
    "name":"x_siesta_input_pao_filter",
    "description":"siesta input variable \"PAO.Filter\"",
    "superNames":["x_siesta_section_input","x_siesta_input"],
    "dtypeStr":"C"
  },{
    "name":"x_siesta_input_pao_fixsplittable",
    "description":"siesta input variable \"PAO.FixSplitTable\"",
    "superNames":["x_siesta_section_input","x_siesta_input"],
    "dtypeStr":"C"
  },{
    "name":"x_siesta_input_pao_keep_findp_bug",
    "description":"siesta input variable \"PAO.Keep.Findp.Bug\"",
    "superNames":["x_siesta_section_input","x_siesta_input"],
    "dtypeStr":"C"
  },{
    "name":"x_siesta_input_pao_newsplitcode",
    "description":"siesta input variable \"PAO.NewSplitCode\"",
    "superNames":["x_siesta_section_input","x_siesta_input"],
    "dtypeStr":"C"
  },{
    "name":"x_siesta_input_pao_oldstylepolorbs",
    "description":"siesta input variable \"PAO.OldStylePolorbs\"",
    "superNames":["x_siesta_section_input","x_siesta_input"],
    "dtypeStr":"C"
  },{
    "name":"x_siesta_input_pao_softdefault",
    "description":"siesta input variable \"PAO.SoftDefault\"",
    "superNames":["x_siesta_section_input","x_siesta_input"],
    "dtypeStr":"C"
  },{
    "name":"x_siesta_input_pao_softinnerradius",
    "description":"siesta input variable \"PAO.SoftInnerRadius\"",
    "superNames":["x_siesta_section_input","x_siesta_input"],
    "dtypeStr":"C"
  },{
    "name":"x_siesta_input_pao_softpotential",
    "description":"siesta input variable \"PAO.SoftPotential\"",
    "superNames":["x_siesta_section_input","x_siesta_input"],
    "dtypeStr":"C"
  },{
    "name":"x_siesta_input_pao_splitnorm",
    "description":"siesta input variable \"PAO.SplitNorm\"",
    "superNames":["x_siesta_section_input","x_siesta_input"],
    "dtypeStr":"C"
  },{
    "name":"x_siesta_input_pao_splitnormh",
    "description":"siesta input variable \"PAO.SplitNormH\"",
    "superNames":["x_siesta_section_input","x_siesta_input"],
    "dtypeStr":"C"
  },{
    "name":"x_siesta_input_pao_splittailnorm",
    "description":"siesta input variable \"PAO.SplitTailNorm\"",
    "superNames":["x_siesta_section_input","x_siesta_input"],
    "dtypeStr":"C"
  },{
    "name":"x_siesta_input_paralleloverk",
    "description":"siesta input variable \"ParallelOverK\"",
    "superNames":["x_siesta_section_input","x_siesta_input"],
    "dtypeStr":"C"
  },{
    "name":"x_siesta_input_partialchargesateverygeometry",
    "description":"siesta input variable \"PartialChargesAtEveryGeometry\"",
    "superNames":["x_siesta_section_input","x_siesta_input"],
    "dtypeStr":"C"
  },{
    "name":"x_siesta_input_partialchargesateveryscfstep",
    "description":"siesta input variable \"PartialChargesAtEveryScfStep\"",
    "superNames":["x_siesta_section_input","x_siesta_input"],
    "dtypeStr":"C"
  },{
    "name":"x_siesta_input_poissonmultigrid",
    "description":"siesta input variable \"PoissonMultigrid\"",
    "superNames":["x_siesta_section_input","x_siesta_input"],
    "dtypeStr":"C"
  },{
    "name":"x_siesta_input_print_ldau",
    "description":"siesta input variable \"Print_ldau\"",
    "superNames":["x_siesta_section_input","x_siesta_input"],
    "dtypeStr":"C"
  },{
    "name":"x_siesta_input_processorgridx",
    "description":"siesta input variable \"ProcessorGridX\"",
    "superNames":["x_siesta_section_input","x_siesta_input"],
    "dtypeStr":"C"
  },{
    "name":"x_siesta_input_processorgridy",
    "description":"siesta input variable \"ProcessorGridY\"",
    "superNames":["x_siesta_section_input","x_siesta_input"],
    "dtypeStr":"C"
  },{
    "name":"x_siesta_input_processorgridz",
    "description":"siesta input variable \"ProcessorGridZ\"",
    "superNames":["x_siesta_section_input","x_siesta_input"],
    "dtypeStr":"C"
  },{
    "name":"x_siesta_input_processory",
    "description":"siesta input variable \"processorY\"",
    "superNames":["x_siesta_section_input","x_siesta_input"],
    "dtypeStr":"C"
  },{
    "name":"x_siesta_input_projectioninscf",
    "description":"siesta input variable \"ProjectionInSCF\"",
    "superNames":["x_siesta_section_input","x_siesta_input"],
    "dtypeStr":"C"
  },{
    "name":"x_siesta_input_projectionmethod",
    "description":"siesta input variable \"ProjectionMethod\"",
    "superNames":["x_siesta_section_input","x_siesta_input"],
    "dtypeStr":"C"
  },{
    "name":"x_siesta_input_ps_sic",
    "description":"siesta input variable \"PS.SIC\"",
    "superNames":["x_siesta_section_input","x_siesta_input"],
    "dtypeStr":"C"
  },{
    "name":"x_siesta_input_rcspatial",
    "description":"siesta input variable \"RcSpatial\"",
    "superNames":["x_siesta_section_input","x_siesta_input"],
    "dtypeStr":"C"
  },{
    "name":"x_siesta_input_readhamiltonian",
    "description":"siesta input variable \"ReadHamiltonian\"",
    "superNames":["x_siesta_section_input","x_siesta_input"],
    "dtypeStr":"C"
  },{
    "name":"x_siesta_input_readkpin",
    "description":"siesta input variable \"ReadKPIN\"",
    "superNames":["x_siesta_section_input","x_siesta_input"],
    "dtypeStr":"C"
  },{
    "name":"x_siesta_input_reinitialisedm",
    "description":"siesta input variable \"ReInitialiseDM\"",
    "superNames":["x_siesta_section_input","x_siesta_input"],
    "dtypeStr":"C"
  },{
    "name":"x_siesta_input_reparametrizepseudos",
    "description":"siesta input variable \"ReparametrizePseudos\"",
    "superNames":["x_siesta_section_input","x_siesta_input"],
    "dtypeStr":"C"
  },{
    "name":"x_siesta_input_restricted_radial_grid",
    "description":"siesta input variable \"Restricted.Radial.Grid\"",
    "superNames":["x_siesta_section_input","x_siesta_input"],
    "dtypeStr":"C"
  },{
    "name":"x_siesta_input_rmax_radial_grid",
    "description":"siesta input variable \"Rmax.Radial.Grid\"",
    "superNames":["x_siesta_section_input","x_siesta_input"],
    "dtypeStr":"C"
  },{
    "name":"x_siesta_input_rotatespin_phi",
    "description":"siesta input variable \"RotateSpin.Phi\"",
    "superNames":["x_siesta_section_input","x_siesta_input"],
    "dtypeStr":"C"
  },{
    "name":"x_siesta_input_rotatespin_theta",
    "description":"siesta input variable \"RotateSpin.Theta\"",
    "superNames":["x_siesta_section_input","x_siesta_input"],
    "dtypeStr":"C"
  },{
    "name":"x_siesta_input_savebadercharge",
    "description":"siesta input variable \"SaveBaderCharge\"",
    "superNames":["x_siesta_section_input","x_siesta_input"],
    "dtypeStr":"C"
  },{
    "name":"x_siesta_input_savedeltarho",
    "description":"siesta input variable \"SaveDeltaRho\"",
    "superNames":["x_siesta_section_input","x_siesta_input"],
    "dtypeStr":"C"
  },{
    "name":"x_siesta_input_saveelectrostaticpotential",
    "description":"siesta input variable \"SaveElectrostaticPotential\"",
    "superNames":["x_siesta_section_input","x_siesta_input"],
    "dtypeStr":"C"
  },{
    "name":"x_siesta_input_savehs",
    "description":"siesta input variable \"SaveHS\"",
    "superNames":["x_siesta_section_input","x_siesta_input"],
    "dtypeStr":"C"
  },{
    "name":"x_siesta_input_saveinitialchargedensity",
    "description":"siesta input variable \"SaveInitialChargeDensity\"",
    "superNames":["x_siesta_section_input","x_siesta_input"],
    "dtypeStr":"C"
  },{
    "name":"x_siesta_input_saveioniccharge",
    "description":"siesta input variable \"SaveIonicCharge\"",
    "superNames":["x_siesta_section_input","x_siesta_input"],
    "dtypeStr":"C"
  },{
    "name":"x_siesta_input_saveneutralatompotential",
    "description":"siesta input variable \"SaveNeutralAtomPotential\"",
    "superNames":["x_siesta_section_input","x_siesta_input"],
    "dtypeStr":"C"
  },{
    "name":"x_siesta_input_saverho",
    "description":"siesta input variable \"SaveRho\"",
    "superNames":["x_siesta_section_input","x_siesta_input"],
    "dtypeStr":"C"
  },{
    "name":"x_siesta_input_saverhoxc",
    "description":"siesta input variable \"SaveRhoXC\"",
    "superNames":["x_siesta_section_input","x_siesta_input"],
    "dtypeStr":"C"
  },{
    "name":"x_siesta_input_savetotalcharge",
    "description":"siesta input variable \"SaveTotalCharge\"",
    "superNames":["x_siesta_section_input","x_siesta_input"],
    "dtypeStr":"C"
  },{
    "name":"x_siesta_input_savetotalpotential",
    "description":"siesta input variable \"SaveTotalPotential\"",
    "superNames":["x_siesta_section_input","x_siesta_input"],
    "dtypeStr":"C"
  },{
    "name":"x_siesta_input_scf_linearmixingafterpulay",
    "description":"siesta input variable \"SCF.LinearMixingAfterPulay\"",
    "superNames":["x_siesta_section_input","x_siesta_input"],
    "dtypeStr":"C"
  },{
    "name":"x_siesta_input_scf_mixafterconvergence",
    "description":"siesta input variable \"SCF.MixAfterConvergence\"",
    "superNames":["x_siesta_section_input","x_siesta_input"],
    "dtypeStr":"C"
  },{
    "name":"x_siesta_input_scf_mixingweightafterpulay",
    "description":"siesta input variable \"SCF.MixingWeightAfterPulay\"",
    "superNames":["x_siesta_section_input","x_siesta_input"],
    "dtypeStr":"C"
  },{
    "name":"x_siesta_input_scf_pulay_damping",
    "description":"siesta input variable \"SCF.Pulay.Damping\"",
    "superNames":["x_siesta_section_input","x_siesta_input"],
    "dtypeStr":"C"
  },{
    "name":"x_siesta_input_scf_pulay_debugsvd",
    "description":"siesta input variable \"SCF.Pulay.DebugSVD\"",
    "superNames":["x_siesta_section_input","x_siesta_input"],
    "dtypeStr":"C"
  },{
    "name":"x_siesta_input_scf_pulay_rcondsvd",
    "description":"siesta input variable \"SCF.Pulay.RcondSVD\"",
    "superNames":["x_siesta_section_input","x_siesta_input"],
    "dtypeStr":"C"
  },{
    "name":"x_siesta_input_scf_pulay_usesvd",
    "description":"siesta input variable \"SCF.Pulay.UseSVD\"",
    "superNames":["x_siesta_section_input","x_siesta_input"],
    "dtypeStr":"C"
  },{
    "name":"x_siesta_input_scf_pulaydmaxregion",
    "description":"siesta input variable \"SCF.PulayDmaxRegion\"",
    "superNames":["x_siesta_section_input","x_siesta_input"],
    "dtypeStr":"C"
  },{
    "name":"x_siesta_input_scf_pulayminimumhistory",
    "description":"siesta input variable \"SCF.PulayMinimumHistory\"",
    "superNames":["x_siesta_section_input","x_siesta_input"],
    "dtypeStr":"C"
  },{
    "name":"x_siesta_input_scf_read_charge_netcdf",
    "description":"siesta input variable \"SCF.Read.Charge.NetCDF\"",
    "superNames":["x_siesta_section_input","x_siesta_input"],
    "dtypeStr":"C"
  },{
    "name":"x_siesta_input_scf_read_deformation_charge_netcdf",
    "description":"siesta input variable \"SCF.Read.Deformation.Charge.NetCDF\"",
    "superNames":["x_siesta_section_input","x_siesta_input"],
    "dtypeStr":"C"
  },{
    "name":"x_siesta_input_scf_recompute_h_after_scf",
    "description":"siesta input variable \"SCF.Recompute-H-After-Scf\"",
    "superNames":["x_siesta_section_input","x_siesta_input"],
    "dtypeStr":"C"
  },{
    "name":"x_siesta_input_scf_want_variational_eks",
    "description":"siesta input variable \"SCF.Want.Variational.EKS\"",
    "superNames":["x_siesta_section_input","x_siesta_input"],
    "dtypeStr":"C"
  },{
    "name":"x_siesta_input_scfmustconverge",
    "description":"siesta input variable \"SCFMustConverge\"",
    "superNames":["x_siesta_section_input","x_siesta_input"],
    "dtypeStr":"C"
  },{
    "name":"x_siesta_input_scissor_operator",
    "description":"siesta input variable \"Scissor.Operator\"",
    "superNames":["x_siesta_section_input","x_siesta_input"],
    "dtypeStr":"C"
  },{
    "name":"x_siesta_input_setbulktransvcell",
    "description":"siesta input variable \"SetBulkTransvCell\"",
    "superNames":["x_siesta_section_input","x_siesta_input"],
    "dtypeStr":"C"
  },{
    "name":"x_siesta_input_sic_flavour",
    "description":"siesta input variable \"SIC.Flavour\"",
    "superNames":["x_siesta_section_input","x_siesta_input"],
    "dtypeStr":"C"
  },{
    "name":"x_siesta_input_sic_lambda",
    "description":"siesta input variable \"SIC.Lambda\"",
    "superNames":["x_siesta_section_input","x_siesta_input"],
    "dtypeStr":"C"
  },{
    "name":"x_siesta_input_sic_norelaxation",
    "description":"siesta input variable \"SIC.NoRelaxation\"",
    "superNames":["x_siesta_section_input","x_siesta_input"],
    "dtypeStr":"C"
  },{
    "name":"x_siesta_input_sic_npop",
    "description":"siesta input variable \"SIC.Npop\"",
    "superNames":["x_siesta_section_input","x_siesta_input"],
    "dtypeStr":"C"
  },{
    "name":"x_siesta_input_sic_popdmconv",
    "description":"siesta input variable \"SIC.PopDMConv\"",
    "superNames":["x_siesta_section_input","x_siesta_input"],
    "dtypeStr":"C"
  },{
    "name":"x_siesta_input_sic_popkgridfactor",
    "description":"siesta input variable \"SIC.PopKgridFactor\"",
    "superNames":["x_siesta_section_input","x_siesta_input"],
    "dtypeStr":"C"
  },{
    "name":"x_siesta_input_sic_popsmatsparsity",
    "description":"siesta input variable \"SIC.PopSmatSparsity\"",
    "superNames":["x_siesta_section_input","x_siesta_input"],
    "dtypeStr":"C"
  },{
    "name":"x_siesta_input_sic_projectionmode",
    "description":"siesta input variable \"SIC.ProjectionMode\"",
    "superNames":["x_siesta_section_input","x_siesta_input"],
    "dtypeStr":"C"
  },{
    "name":"x_siesta_input_sic_projectiontype",
    "description":"siesta input variable \"SIC.ProjectionType\"",
    "superNames":["x_siesta_section_input","x_siesta_input"],
    "dtypeStr":"C"
  },{
    "name":"x_siesta_input_sic_rot_inv",
    "description":"siesta input variable \"SIC.Rot_Inv\"",
    "superNames":["x_siesta_section_input","x_siesta_input"],
    "dtypeStr":"C"
  },{
    "name":"x_siesta_input_siesta2wannier90_numberofbands",
    "description":"siesta input variable \"Siesta2Wannier90.NumberOfBands\"",
    "superNames":["x_siesta_section_input","x_siesta_input"],
    "dtypeStr":"C"
  },{
    "name":"x_siesta_input_siesta2wannier90_numberofbandsdown",
    "description":"siesta input variable \"Siesta2Wannier90.NumberOfBandsDown\"",
    "superNames":["x_siesta_section_input","x_siesta_input"],
    "dtypeStr":"C"
  },{
    "name":"x_siesta_input_siesta2wannier90_numberofbandsup",
    "description":"siesta input variable \"Siesta2Wannier90.NumberOfBandsUp\"",
    "superNames":["x_siesta_section_input","x_siesta_input"],
    "dtypeStr":"C"
  },{
    "name":"x_siesta_input_siesta2wannier90_writeamn",
    "description":"siesta input variable \"Siesta2Wannier90.WriteAmn\"",
    "superNames":["x_siesta_section_input","x_siesta_input"],
    "dtypeStr":"C"
  },{
    "name":"x_siesta_input_siesta2wannier90_writeeig",
    "description":"siesta input variable \"Siesta2Wannier90.WriteEig\"",
    "superNames":["x_siesta_section_input","x_siesta_input"],
    "dtypeStr":"C"
  },{
    "name":"x_siesta_input_siesta2wannier90_writemmn",
    "description":"siesta input variable \"Siesta2Wannier90.WriteMmn\"",
    "superNames":["x_siesta_section_input","x_siesta_input"],
    "dtypeStr":"C"
  },{
    "name":"x_siesta_input_siesta2wannier90_writeunk",
    "description":"siesta input variable \"Siesta2Wannier90.WriteUnk\"",
    "superNames":["x_siesta_section_input","x_siesta_input"],
    "dtypeStr":"C"
  },{
    "name":"x_siesta_input_sigma_dsigmade",
    "description":"siesta input variable \"Sigma.DSigmaDE\"",
    "superNames":["x_siesta_section_input","x_siesta_input"],
    "dtypeStr":"C"
  },{
    "name":"x_siesta_input_signaturerecords",
    "description":"siesta input variable \"SignatureRecords\"",
    "superNames":["x_siesta_section_input","x_siesta_input"],
    "dtypeStr":"C"
  },{
    "name":"x_siesta_input_simulatedoping",
    "description":"siesta input variable \"SimulateDoping\"",
    "superNames":["x_siesta_section_input","x_siesta_input"],
    "dtypeStr":"C"
  },{
    "name":"x_siesta_input_singleexcitation",
    "description":"siesta input variable \"SingleExcitation\"",
    "superNames":["x_siesta_section_input","x_siesta_input"],
    "dtypeStr":"C"
  },{
    "name":"x_siesta_input_skiplastiter",
    "description":"siesta input variable \"SkipLastIter\"",
    "superNames":["x_siesta_section_input","x_siesta_input"],
    "dtypeStr":"C"
  },{
    "name":"x_siesta_input_slabdipolecorrection",
    "description":"siesta input variable \"SlabDipoleCorrection\"",
    "superNames":["x_siesta_section_input","x_siesta_input"],
    "dtypeStr":"C"
  },{
    "name":"x_siesta_input_solutionmethod",
    "description":"siesta input variable \"SolutionMethod\"",
    "superNames":["x_siesta_section_input","x_siesta_input"],
    "dtypeStr":"C"
  },{
    "name":"x_siesta_input_spinconfleads",
    "description":"siesta input variable \"SpinConfLeads\"",
    "superNames":["x_siesta_section_input","x_siesta_input"],
    "dtypeStr":"C"
  },{
    "name":"x_siesta_input_spinorbit",
    "description":"siesta input variable \"SpinOrbit\"",
    "superNames":["x_siesta_section_input","x_siesta_input"],
    "dtypeStr":"C"
  },{
    "name":"x_siesta_input_spinpolarized",
    "description":"siesta input variable \"SpinPolarized\"",
    "superNames":["x_siesta_section_input","x_siesta_input"],
    "dtypeStr":"C"
  },{
    "name":"x_siesta_input_stt_calculation",
    "description":"siesta input variable \"STT.Calculation\"",
    "superNames":["x_siesta_section_input","x_siesta_input"],
    "dtypeStr":"C"
  },{
    "name":"x_siesta_input_stt_linearresponse",
    "description":"siesta input variable \"STT.LinearResponse\"",
    "superNames":["x_siesta_section_input","x_siesta_input"],
    "dtypeStr":"C"
  },{
    "name":"x_siesta_input_systemlabel",
    "description":"siesta input variable \"SystemLabel\"",
    "superNames":["x_siesta_section_input","x_siesta_input"],
    "dtypeStr":"C"
  },{
    "name":"x_siesta_input_systemname",
    "description":"siesta input variable \"SystemName\"",
    "superNames":["x_siesta_section_input","x_siesta_input"],
    "dtypeStr":"C"
  },{
    "name":"x_siesta_input_timer_report_threshold",
    "description":"siesta input variable \"timer_report_threshold\"",
    "superNames":["x_siesta_section_input","x_siesta_input"],
    "dtypeStr":"C"
  },{
    "name":"x_siesta_input_timereversal",
    "description":"siesta input variable \"TimeReversal\"",
    "superNames":["x_siesta_section_input","x_siesta_input"],
    "dtypeStr":"C"
  },{
    "name":"x_siesta_input_timereversalsymmetryforkpoints",
    "description":"siesta input variable \"TimeReversalSymmetryForKpoints\"",
    "superNames":["x_siesta_section_input","x_siesta_input"],
    "dtypeStr":"C"
  },{
    "name":"x_siesta_input_trcoefficients",
    "description":"siesta input variable \"TrCoefficients\"",
    "superNames":["x_siesta_section_input","x_siesta_input"],
    "dtypeStr":"C"
  },{
    "name":"x_siesta_input_trymemoryincrease",
    "description":"siesta input variable \"TryMemoryIncrease\"",
    "superNames":["x_siesta_section_input","x_siesta_input"],
    "dtypeStr":"C"
  },{
    "name":"x_siesta_input_ts_mixh",
    "description":"siesta input variable \"TS.MixH\"",
    "superNames":["x_siesta_section_input","x_siesta_input"],
    "dtypeStr":"C"
  },{
    "name":"x_siesta_input_usedomaindecomposition",
    "description":"siesta input variable \"UseDomainDecomposition\"",
    "superNames":["x_siesta_section_input","x_siesta_input"],
    "dtypeStr":"C"
  },{
    "name":"x_siesta_input_usenewdiagk",
    "description":"siesta input variable \"UseNewDiagk\"",
    "superNames":["x_siesta_section_input","x_siesta_input"],
    "dtypeStr":"C"
  },{
    "name":"x_siesta_input_user_basis",
    "description":"siesta input variable \"user-basis\"",
    "superNames":["x_siesta_section_input","x_siesta_input"],
    "dtypeStr":"C"
  },{
    "name":"x_siesta_input_user_basis_netcdf",
    "description":"siesta input variable \"user-basis-netcdf\"",
    "superNames":["x_siesta_section_input","x_siesta_input"],
    "dtypeStr":"C"
  },{
    "name":"x_siesta_input_usesavedata",
    "description":"siesta input variable \"UseSaveData\"",
    "superNames":["x_siesta_section_input","x_siesta_input"],
    "dtypeStr":"C"
  },{
    "name":"x_siesta_input_usespatialdecomposition",
    "description":"siesta input variable \"UseSpatialDecomposition\"",
    "superNames":["x_siesta_section_input","x_siesta_input"],
    "dtypeStr":"C"
  },{
    "name":"x_siesta_input_usestructfile",
    "description":"siesta input variable \"UseStructFile\"",
    "superNames":["x_siesta_section_input","x_siesta_input"],
    "dtypeStr":"C"
  },{
    "name":"x_siesta_input_usetreetimer",
    "description":"siesta input variable \"UseTreeTimer\"",
    "superNames":["x_siesta_section_input","x_siesta_input"],
    "dtypeStr":"C"
  },{
    "name":"x_siesta_input_vfinal",
    "description":"siesta input variable \"VFinal\"",
    "superNames":["x_siesta_section_input","x_siesta_input"],
    "dtypeStr":"C"
  },{
    "name":"x_siesta_input_vgate",
    "description":"siesta input variable \"VGate\"",
    "superNames":["x_siesta_section_input","x_siesta_input"],
    "dtypeStr":"C"
  },{
    "name":"x_siesta_input_vinitial",
    "description":"siesta input variable \"VInitial\"",
    "superNames":["x_siesta_section_input","x_siesta_input"],
    "dtypeStr":"C"
  },{
    "name":"x_siesta_input_vna_filter",
    "description":"siesta input variable \"Vna.Filter\"",
    "superNames":["x_siesta_section_input","x_siesta_input"],
    "dtypeStr":"C"
  },{
    "name":"x_siesta_input_warningminimumatomicdistance",
    "description":"siesta input variable \"WarningMinimumAtomicDistance\"",
    "superNames":["x_siesta_section_input","x_siesta_input"],
    "dtypeStr":"C"
  },{
    "name":"x_siesta_input_writebands",
    "description":"siesta input variable \"WriteBands\"",
    "superNames":["x_siesta_section_input","x_siesta_input"],
    "dtypeStr":"C"
  },{
    "name":"x_siesta_input_writecoorcerius",
    "description":"siesta input variable \"WriteCoorCerius\"",
    "superNames":["x_siesta_section_input","x_siesta_input"],
    "dtypeStr":"C"
  },{
    "name":"x_siesta_input_writecoorinitial",
    "description":"siesta input variable \"WriteCoorInitial\"",
    "superNames":["x_siesta_section_input","x_siesta_input"],
    "dtypeStr":"C"
  },{
    "name":"x_siesta_input_writecoorstep",
    "description":"siesta input variable \"WriteCoorStep\"",
    "superNames":["x_siesta_section_input","x_siesta_input"],
    "dtypeStr":"C"
  },{
    "name":"x_siesta_input_writecoorxmol",
    "description":"siesta input variable \"WriteCoorXmol\"",
    "superNames":["x_siesta_section_input","x_siesta_input"],
    "dtypeStr":"C"
  },{
    "name":"x_siesta_input_writedenchar",
    "description":"siesta input variable \"WriteDenchar\"",
    "superNames":["x_siesta_section_input","x_siesta_input"],
    "dtypeStr":"C"
  },{
    "name":"x_siesta_input_writediagds",
    "description":"siesta input variable \"WriteDiagdS\"",
    "superNames":["x_siesta_section_input","x_siesta_input"],
    "dtypeStr":"C"
  },{
    "name":"x_siesta_input_writedm",
    "description":"siesta input variable \"WriteDM\"",
    "superNames":["x_siesta_section_input","x_siesta_input"],
    "dtypeStr":"C"
  },{
    "name":"x_siesta_input_writedm_history_netcdf",
    "description":"siesta input variable \"WriteDM.History.NetCDF\"",
    "superNames":["x_siesta_section_input","x_siesta_input"],
    "dtypeStr":"C"
  },{
    "name":"x_siesta_input_writedm_netcdf",
    "description":"siesta input variable \"WriteDM.NetCDF\"",
    "superNames":["x_siesta_section_input","x_siesta_input"],
    "dtypeStr":"C"
  },{
    "name":"x_siesta_input_writedmhs_history_netcdf",
    "description":"siesta input variable \"WriteDMHS.History.NetCDF\"",
    "superNames":["x_siesta_section_input","x_siesta_input"],
    "dtypeStr":"C"
  },{
    "name":"x_siesta_input_writedmhs_netcdf",
    "description":"siesta input variable \"WriteDMHS.NetCDF\"",
    "superNames":["x_siesta_section_input","x_siesta_input"],
    "dtypeStr":"C"
  },{
    "name":"x_siesta_input_writedmt",
    "description":"siesta input variable \"WriteDMT\"",
    "superNames":["x_siesta_section_input","x_siesta_input"],
    "dtypeStr":"C"
  },{
    "name":"x_siesta_input_writeedm",
    "description":"siesta input variable \"WriteEDM\"",
    "superNames":["x_siesta_section_input","x_siesta_input"],
    "dtypeStr":"C"
  },{
    "name":"x_siesta_input_writeeigenvalues",
    "description":"siesta input variable \"WriteEigenvalues\"",
    "superNames":["x_siesta_section_input","x_siesta_input"],
    "dtypeStr":"C"
  },{
    "name":"x_siesta_input_writeforces",
    "description":"siesta input variable \"WriteForces\"",
    "superNames":["x_siesta_section_input","x_siesta_input"],
    "dtypeStr":"C"
  },{
    "name":"x_siesta_input_writehamiltonpop",
    "description":"siesta input variable \"WriteHamiltonPop\"",
    "superNames":["x_siesta_section_input","x_siesta_input"],
    "dtypeStr":"C"
  },{
    "name":"x_siesta_input_writehirshfeldpop",
    "description":"siesta input variable \"WriteHirshfeldPop\"",
    "superNames":["x_siesta_section_input","x_siesta_input"],
    "dtypeStr":"C"
  },{
    "name":"x_siesta_input_writehsderiv",
    "description":"siesta input variable \"WriteHSDeriv\"",
    "superNames":["x_siesta_section_input","x_siesta_input"],
    "dtypeStr":"C"
  },{
    "name":"x_siesta_input_writeionplotfiles",
    "description":"siesta input variable \"WriteIonPlotFiles\"",
    "superNames":["x_siesta_section_input","x_siesta_input"],
    "dtypeStr":"C"
  },{
    "name":"x_siesta_input_writekbands",
    "description":"siesta input variable \"WriteKbands\"",
    "superNames":["x_siesta_section_input","x_siesta_input"],
    "dtypeStr":"C"
  },{
    "name":"x_siesta_input_writekpoints",
    "description":"siesta input variable \"WriteKpoints\"",
    "superNames":["x_siesta_section_input","x_siesta_input"],
    "dtypeStr":"C"
  },{
    "name":"x_siesta_input_writemdhistory",
    "description":"siesta input variable \"WriteMDhistory\"",
    "superNames":["x_siesta_section_input","x_siesta_input"],
    "dtypeStr":"C"
  },{
    "name":"x_siesta_input_writemdxmol",
    "description":"siesta input variable \"WriteMDXmol\"",
    "superNames":["x_siesta_section_input","x_siesta_input"],
    "dtypeStr":"C"
  },{
    "name":"x_siesta_input_writemullikenpop",
    "description":"siesta input variable \"WriteMullikenPop\"",
    "superNames":["x_siesta_section_input","x_siesta_input"],
    "dtypeStr":"C"
  },{
    "name":"x_siesta_input_writeprojections",
    "description":"siesta input variable \"WriteProjections\"",
    "superNames":["x_siesta_section_input","x_siesta_input"],
    "dtypeStr":"C"
  },{
    "name":"x_siesta_input_writespinmulliken",
    "description":"siesta input variable \"WriteSpinMulliken\"",
    "superNames":["x_siesta_section_input","x_siesta_input"],
    "dtypeStr":"C"
  },{
    "name":"x_siesta_input_writespinscf",
    "description":"siesta input variable \"WriteSpinSCF\"",
    "superNames":["x_siesta_section_input","x_siesta_input"],
    "dtypeStr":"C"
  },{
    "name":"x_siesta_input_writevna",
    "description":"siesta input variable \"WriteVNA\"",
    "superNames":["x_siesta_section_input","x_siesta_input"],
    "dtypeStr":"C"
  },{
    "name":"x_siesta_input_writevoronoipop",
    "description":"siesta input variable \"WriteVoronoiPop\"",
    "superNames":["x_siesta_section_input","x_siesta_input"],
    "dtypeStr":"C"
  },{
    "name":"x_siesta_input_writewavefunctions",
    "description":"siesta input variable \"WriteWaveFunctions\"",
    "superNames":["x_siesta_section_input","x_siesta_input"],
    "dtypeStr":"C"
  },{
    "name":"x_siesta_input_xc_authors",
    "description":"siesta input variable \"xc.authors\"",
    "superNames":["x_siesta_section_input","x_siesta_input"],
    "dtypeStr":"C"
  },{
    "name":"x_siesta_input_xc_functional",
    "description":"siesta input variable \"xc.functional\"",
    "superNames":["x_siesta_section_input","x_siesta_input"],
    "dtypeStr":"C"
  },{
    "name":"x_siesta_input_xml_abortonerrors",
    "description":"siesta input variable \"XML.AbortOnErrors\"",
    "superNames":["x_siesta_section_input","x_siesta_input"],
    "dtypeStr":"C"
  },{
    "name":"x_siesta_input_xml_abortonwarnings",
    "description":"siesta input variable \"XML.AbortOnWarnings\"",
    "superNames":["x_siesta_section_input","x_siesta_input"],
    "dtypeStr":"C"
  },{
    "name":"x_siesta_input_xml_write",
    "description":"siesta input variable \"XML.Write\"",
    "superNames":["x_siesta_section_input","x_siesta_input"],
    "dtypeStr":"C"
  },{
    "name":"x_siesta_input_zbroadeningg",
    "description":"siesta input variable \"ZBroadeningG\"",
    "superNames":["x_siesta_section_input","x_siesta_input"],
    "dtypeStr":"C"
  },{
    "name":"x_siesta_input_zeemantermbx",
    "description":"siesta input variable \"ZeemanTermBx\"",
    "superNames":["x_siesta_section_input","x_siesta_input"],
    "dtypeStr":"C"
  },{
    "name":"x_siesta_input_zeemantermby",
    "description":"siesta input variable \"ZeemanTermBy\"",
    "superNames":["x_siesta_section_input","x_siesta_input"],
    "dtypeStr":"C"
  },{
    "name":"x_siesta_input_zeemantermbz",
    "description":"siesta input variable \"ZeemanTermBz\"",
    "superNames":["x_siesta_section_input","x_siesta_input"],
    "dtypeStr":"C"
  },{
    "name":"x_siesta_input_zleftvcte",
    "description":"siesta input variable \"ZLeftVcte\"",
    "superNames":["x_siesta_section_input","x_siesta_input"],
    "dtypeStr":"C"
  },{
    "name":"x_siesta_input_zm_calcallforces",
    "description":"siesta input variable \"ZM.CalcAllForces\"",
    "superNames":["x_siesta_section_input","x_siesta_input"],
    "dtypeStr":"C"
  },{
    "name":"x_siesta_input_zm_forcetolangle",
    "description":"siesta input variable \"ZM.ForceTolAngle\"",
    "superNames":["x_siesta_section_input","x_siesta_input"],
    "dtypeStr":"C"
  },{
    "name":"x_siesta_input_zm_forcetollength",
    "description":"siesta input variable \"ZM.ForceTolLength\"",
    "superNames":["x_siesta_section_input","x_siesta_input"],
    "dtypeStr":"C"
  },{
    "name":"x_siesta_input_zm_maxdisplangle",
    "description":"siesta input variable \"ZM.MaxDisplAngle\"",
    "superNames":["x_siesta_section_input","x_siesta_input"],
    "dtypeStr":"C"
  },{
    "name":"x_siesta_input_zm_maxdispllength",
    "description":"siesta input variable \"ZM.MaxDisplLength\"",
    "superNames":["x_siesta_section_input","x_siesta_input"],
    "dtypeStr":"C"
  },{
    "name":"x_siesta_input_zm_unitsangle",
    "description":"siesta input variable \"ZM.UnitsAngle\"",
    "superNames":["x_siesta_section_input","x_siesta_input"],
    "dtypeStr":"C"
  },{
    "name":"x_siesta_input_zm_unitslength",
    "description":"siesta input variable \"ZM.UnitsLength\"",
    "superNames":["x_siesta_section_input","x_siesta_input"],
    "dtypeStr":"C"
  },{
    "name":"x_siesta_input_zrightvcte",
    "description":"siesta input variable \"ZRightVcte\"",
    "superNames":["x_siesta_section_input","x_siesta_input"],
    "dtypeStr":"C"
  },{
    "name":"x_siesta_input_zvgatel",
    "description":"siesta input variable \"ZVGateL\"",
    "superNames":["x_siesta_section_input","x_siesta_input"],
    "dtypeStr":"C"
  },{
    "name":"x_siesta_input_zvgater",
    "description":"siesta input variable \"ZVGateR\"",
    "superNames":["x_siesta_section_input","x_siesta_input"],
    "dtypeStr":"C"
  },{
    "name":"x_siesta_section_input",
    "kindStr":"type_section",
    "description":"input section",
    "superNames":["section_method"]
  }]
}
