{
  "metadict_name":"octopus",
  "metadict_description":[
    "meta info used by the octopus parser, all names are expected to start with ",
    "x_octopus_"],
  "metadict_version":"0.1",
  "metadict_require":[{
    "metadict_required_name":"octopus_autogenerated"
  },{
    "metadict_required_name":"common"
  }],
  "meta_info_entry":[{
    "meta_name":"x_octopus_info_energy_ion_ion",
    "meta_type":"type-value",
    "meta_description":"ion-ion interaction energy",
    "meta_parent_section":"section_single_configuration_calculation",
    "meta_data_type":"float"
  },{
    "meta_name":"x_octopus_info_scf_converged_iterations",
    "meta_type":"type-value",
    "meta_description":"number of scf iterations to converge calculation",
    "meta_parent_section":"section_run",
    "meta_data_type":"int"
  },{
    "meta_name":"x_octopus_log_svn_revision",
    "meta_type":"type-value",
    "meta_description":"octopus svn revision",
    "meta_parent_section":"section_run",
    "meta_data_type":"int"
  }]
}
